v1dd_physiology/__init__.py
v1dd_physiology/nwb_building/__init__.py
v1dd_physiology-0.1.dist-info/LICENSE
v1dd_physiology-0.1.dist-info/METADATA
v1dd_physiology-0.1.dist-info/WHEEL
v1dd_physiology-0.1.dist-info/top_level.txt
v1dd_physiology-0.1.dist-info/RECORD
