Metadata-Version: 2.1
Name: v1dd-physiology
Version: 0.1
Summary: SDK for volumetric multi-photon data of V1 DeepDive project
Home-page: https://github.com/AllenInstitute/v1dd_physiology.git
Author: Allen Institute
Author-email: junz@alleninstitute.org
License: UNKNOWN
Platform: any
Classifier: Programming Language :: Python
Classifier: Development Status :: 4 - Beta
Classifier: Natural Language :: English
Classifier: Operating System :: OS Independent
Requires-Python: >3.8
License-File: LICENSE
Requires-Dist: cython
Requires-Dist: scikit-image
Requires-Dist: pillow
Requires-Dist: pytest
Requires-Dist: opencv-python
Requires-Dist: tifffile
Requires-Dist: h5py
Requires-Dist: pandas
Requires-Dist: matplotlib
Requires-Dist: scipy
Requires-Dist: numpy
Requires-Dist: NeuroAnalysisTools
